LICENSE
MANIFEST.in
README.rst
setup.cfg
setup.py
doc/Makefile
doc/api.rst
doc/basic_use.rst
doc/changelog.rst
doc/conf.py
doc/future.rst
doc/incompatibilities.rst
doc/index.rst
doc/installation.rst
doc/make.bat
doc/output.rst
doc/images/sample_plotmetric.png
measure_it/__init__.py
measure_it/csv.py
measure_it/numpy.py
measure_it/statsd.py
measure_it.egg-info/PKG-INFO
measure_it.egg-info/SOURCES.txt
measure_it.egg-info/dependency_links.txt
measure_it.egg-info/requires.txt
measure_it.egg-info/top_level.txt
tests/__init__.py
tests/test_csv.py
tests/test_numpy.py