Metadata-Version: 1.1
Name: measure-it
Version: 0.4
Summary: time and count measurement for iterators and other code
Home-page: http://github.com/wearpants/measure_it
Author: Pete Fein
Author-email: pete@wearpants.org
License: BSD
Platform: UNKNOWN
Classifier: Programming Language :: Python :: 2
Classifier: Programming Language :: Python :: 3
Classifier: Development Status :: 5 - Production/Stable
Classifier: Intended Audience :: Developers
Classifier: License :: OSI Approved :: BSD License
